Workbook

Sheet Requirements
A1: Requirement ID | B1: Requirement Type | C1: Requirement Description | D1: Requirements Status | E1: Review Comments | F1: Product Release | G1: Test Case ID | H1: Test Type | I1: Test Case Description | J1: Test Case Status | K1: Linked Requirements
A2: =IF(B2="","",CONCATENATE(Configuration!$A$2,"_",ROW(B2)-1)) -> ATP_ProdSpec_1 | B2: Heading | C2: General | D2: Reviewed | G2: =IF(OR(H2="No",H2=""),"",CONCATENATE(Configuration!$A$2,"_TC_",ROW(B2)-1)) | H2: No
A3: =IF(B3="","",CONCATENATE(Configuration!$A$2,"_",ROW(B3)-1)) -> ATP_ProdSpec_2 | B3: Sub-heading | C3: Definition of terms | D3: Reviewed | G3: =IF(OR(H3="No",H3=""),"",CONCATENATE(Configuration!$A$2,"_TC_",ROW(B3)-1)) | H3: No
A4: =IF(B4="","",CONCATENATE(Configuration!$A$2,"_",ROW(B4)-1)) -> ATP_ProdSpec_3 | B4: Information | C4: 02_ReqMgn/CommonDefinitionOfTermsAndAbbreviations.xlsx | D4: Reviewed | G4: =IF(OR(H4="No",H4=""),"",CONCATENATE(Configuration!$A$2,"_TC_",ROW(B4)-1)) | H4: No
A5: =IF(B5="","",CONCATENATE(Configuration!$A$2,"_",ROW(B5)-1)) -> ATP_ProdSpec_4 | B5: Sub-heading | C5: Abbreviations | D5: Reviewed | G5: =IF(OR(H5="No",H5=""),"",CONCATENATE(Configuration!$A$2,"_TC_",ROW(B5)-1)) | H5: No
A6: =IF(B6="","",CONCATENATE(Configuration!$A$2,"_",ROW(B6)-1)) -> ATP_ProdSpec_5 | B6: Information | C6: 02_ReqMgn/CommonDefinitionOfTermsAndAbbreviations.xlsx | D6: Reviewed | G6: =IF(OR(H6="No",H6=""),"",CONCATENATE(Configuration!$A$2,"_TC_",ROW(B6)-1)) | H6: No
A7: =IF(B7="","",CONCATENATE(Configuration!$A$2,"_",ROW(B7)-1)) -> ATP_ProdSpec_6 | B7: Heading | C7: Product purpose and description | D7: Reviewed | G7: =IF(OR(H7="No",H7=""),"",CONCATENATE(Configuration!$A$2,"_TC_",ROW(B7)-1)) | H7: No
A8: =IF(B8="","",CONCATENATE(Configuration!$A$2,"_",ROW(B8)-1)) -> ATP_ProdSpec_7 | B8: Information | C8: The purpose of the product is to partially or fully automate the manual trading of bonds, stocks, forex, crypto, etc. Here, the product is intended to support the effective and efficient use of trading time, as well as to minimize the use of personal lifetime for trading and to maximize the personal monetary profit. The goal is to be achieved by AI traders who trade automatically on accessible exchanges based on technical analysis, the experience of experts and their own experience, and use their information, such as charts and indicators. To achieve this, the user should be able to configure any number of configurable AI traders (e.g. which stock exchange should be used, which risk profile, how much budget, which trading strategies, etc.), which are based on trading profiles provided by the user (third-party povider). The performance and risk classification of the product and the product updates are evaluated, proven and improved via demo accounts. | D8: New | G8: =IF(OR(H8="No",H8=""),"",CONCATENATE(Configuration!$A$2,"_TC_",ROW(B8)-1))
A9: =IF(B9="","",CONCATENATE(Configuration!$A$2,"_",ROW(B9)-1)) -> ATP_ProdSpec_8 | B9: Information | C9: The relevant trading classes of the product - Bonds - CFDs - Cryptos - ETFs - NFTs - Private Equity - Raw Materials - Stocks | D9: New | G9: =IF(OR(H9="No",H9=""),"",CONCATENATE(Configuration!$A$2,"_TC_",ROW(B9)-1))
A10: =IF(B10="","",CONCATENATE(Configuration!$A$2,"_",ROW(B10)-1)) -> ATP_ProdSpec_9 | B10: Information | C10: The relevant devices of the product - personal computer - notebook - tablet - smartphone - smartwatch | G10: =IF(OR(H10="No",H10=""),"",CONCATENATE(Configuration!$A$2,"_TC_",ROW(B10)-1))
A11: =IF(B11="","",CONCATENATE(Configuration!$A$2,"_",ROW(B11)-1)) -> ATP_ProdSpec_10 | B11: Heading | C11: Product architecture | D11: Reviewed | G11: =IF(OR(H11="No",H11=""),"",CONCATENATE(Configuration!$A$2,"_TC_",ROW(B11)-1)) | H11: No
A12: =IF(B12="","",CONCATENATE(Configuration!$A$2,"_",ROW(B12)-1)) -> ATP_ProdSpec_11 | B12: Information | C12: #VALUE! | D12: Reviewed | G12: =IF(OR(H12="No",H12=""),"",CONCATENATE(Configuration!$A$2,"_TC_",ROW(B12)-1))
A13: =IF(B13="","",CONCATENATE(Configuration!$A$2,"_",ROW(B13)-1)) -> ATP_ProdSpec_12 | B13: Sub-heading | C13: UI Application | D13: Reviewed | G13: =IF(OR(H13="No",H13=""),"",CONCATENATE(Configuration!$A$2,"_TC_",ROW(B13)-1))
A14: =IF(B14="","",CONCATENATE(Configuration!$A$2,"_",ROW(B14)-1)) -> ATP_ProdSpec_13 | B14: Function | C14: The UI Application shall connect the User with the Core Application | D14: New | G14: =IF(OR(H14="No",H14=""),"",CONCATENATE(Configuration!$A$2,"_TC_",ROW(B14)-1))
A15: =IF(B15="","",CONCATENATE(Configuration!$A$2,"_",ROW(B15)-1)) -> ATP_ProdSpec_14 | B15: Non Function | C15: The UI Application shall be available on all computer-like devices (e.g. personal computer, notebook, tablet, smartphone, smartwatch) | G15: =IF(OR(H15="No",H15=""),"",CONCATENATE(Configuration!$A$2,"_TC_",ROW(B15)-1))
A16: =IF(B16="","",CONCATENATE(Configuration!$A$2,"_",ROW(B16)-1)) -> ATP_ProdSpec_15 | B16: Function | C16: The UI Application shall allow the user to select the exchange they wish to use for trading and to configure their existing account for the exchange | G16: =IF(OR(H16="No",H16=""),"",CONCATENATE(Configuration!$A$2,"_TC_",ROW(B16)-1))
A17: =IF(B17="","",CONCATENATE(Configuration!$A$2,"_",ROW(B17)-1)) -> ATP_ProdSpec_16 | B17: Function | C17: The UI Application shall be the command center to create, re-configure and observe the AI trader by the user, as well as providing a real-time overview of the status and trading success of the AI trader | G17: =IF(OR(H17="No",H17=""),"",CONCATENATE(Configuration!$A$2,"_TC_",ROW(B17)-1))
A18: =IF(B18="","",CONCATENATE(Configuration!$A$2,"_",ROW(B18)-1)) -> ATP_ProdSpec_17 | B18: Sub-heading | C18: Core Application | G18: =IF(OR(H18="No",H18=""),"",CONCATENATE(Configuration!$A$2,"_TC_",ROW(B18)-1))
A19: =IF(B19="","",CONCATENATE(Configuration!$A$2,"_",ROW(B19)-1)) -> ATP_ProdSpec_18 | B19: Function | C19: The Core Application shall connect User Interface, Trading Knowledge Database and Third-Party Products (e.g. Exchange, Information) | G19: =IF(OR(H19="No",H19=""),"",CONCATENATE(Configuration!$A$2,"_TC_",ROW(B19)-1))
A20: =IF(B20="","",CONCATENATE(Configuration!$A$2,"_",ROW(B20)-1)) -> ATP_ProdSpec_19 | B20: Non Function | C20: The Core Application shall be available 24/7 from the computer-like devices | G20: =IF(OR(H20="No",H20=""),"",CONCATENATE(Configuration!$A$2,"_TC_",ROW(B20)-1))
A21: =IF(B21="","",CONCATENATE(Configuration!$A$2,"_",ROW(B21)-1)) -> ATP_ProdSpec_20 | B21: Function | C21: The Core Application shall provide connectors to the computer-like devices | G21: =IF(OR(H21="No",H21=""),"",CONCATENATE(Configuration!$A$2,"_TC_",ROW(B21)-1))
A22: =IF(B22="","",CONCATENATE(Configuration!$A$2,"_",ROW(B22)-1)) -> ATP_ProdSpec_21 | B22: Function | C22: The Core Application shall provide connectors to the stock exchanges | G22: =IF(OR(H22="No",H22=""),"",CONCATENATE(Configuration!$A$2,"_TC_",ROW(B22)-1))
A23: =IF(B23="","",CONCATENATE(Configuration!$A$2,"_",ROW(B23)-1)) -> ATP_ProdSpec_22 | B23: Function | C23: The Core Application shall provide connectors to the market information applications | G23: =IF(OR(H23="No",H23=""),"",CONCATENATE(Configuration!$A$2,"_TC_",ROW(B23)-1))
A24: =IF(B24="","",CONCATENATE(Configuration!$A$2,"_",ROW(B24)-1)) -> ATP_ProdSpec_23 | B24: Function | C24: The Core Application shall provide the secure access between the connectors and the core application | D24: New | G24: =IF(OR(H24="No",H24=""),"",CONCATENATE(Configuration!$A$2,"_TC_",ROW(B24)-1))
A25: =IF(B25="","",CONCATENATE(Configuration!$A$2,"_",ROW(B25)-1)) -> ATP_ProdSpec_24 | B25: Function | C25: The Core Application shall provide the access and training of trading knowlede | G25: =IF(OR(H25="No",H25=""),"",CONCATENATE(Configuration!$A$2,"_TC_",ROW(B25)-1))
A26: =IF(B26="","",CONCATENATE(Configuration!$A$2,"_",ROW(B26)-1)) -> ATP_ProdSpec_25 | B26: Function | C26: The Core Application shall provide the trading algorithm | G26: =IF(OR(H26="No",H26=""),"",CONCATENATE(Configuration!$A$2,"_TC_",ROW(B26)-1))
A27: =IF(B27="","",CONCATENATE(Configuration!$A$2,"_",ROW(B27)-1)) -> ATP_ProdSpec_26 | B27: Function | C27: The Core Application shall provide a power lifecycle strategy | G27: =IF(OR(H27="No",H27=""),"",CONCATENATE(Configuration!$A$2,"_TC_",ROW(B27)-1))
A28: =IF(B28="","",CONCATENATE(Configuration!$A$2,"_",ROW(B28)-1)) -> ATP_ProdSpec_27 | B28: Function | C28: The Core Application shall provide a error and healing strategy | G28: =IF(OR(H28="No",H28=""),"",CONCATENATE(Configuration!$A$2,"_TC_",ROW(B28)-1))
A29: =IF(B29="","",CONCATENATE(Configuration!$A$2,"_",ROW(B29)-1)) -> ATP_ProdSpec_28 | B29: Sub-heading | C29: Trading Knowledge Database | G29: =IF(OR(H29="No",H29=""),"",CONCATENATE(Configuration!$A$2,"_TC_",ROW(B29)-1))
A30: =IF(B30="","",CONCATENATE(Configuration!$A$2,"_",ROW(B30)-1)) -> ATP_ProdSpec_29 | B30: Function | C30: The Trading Knowledge Database shall provide the trading experience to the Core Application | D30: New | G30: =IF(OR(H30="No",H30=""),"",CONCATENATE(Configuration!$A$2,"_TC_",ROW(B30)-1))
A31: =IF(B31="","",CONCATENATE(Configuration!$A$2,"_",ROW(B31)-1)) -> ATP_ProdSpec_30 | B31: Function | C31: The trading experience shall be used by the AI traders | G31: =IF(OR(H31="No",H31=""),"",CONCATENATE(Configuration!$A$2,"_TC_",ROW(B31)-1))
A32: =IF(B32="","",CONCATENATE(Configuration!$A$2,"_",ROW(B32)-1)) -> ATP_ProdSpec_31 | B32: Sub-heading | C32: Stock Exchange Application (third-party provider) | G32: =IF(OR(H32="No",H32=""),"",CONCATENATE(Configuration!$A$2,"_TC_",ROW(B32)-1))
A33: =IF(B33="","",CONCATENATE(Configuration!$A$2,"_",ROW(B33)-1)) -> ATP_ProdSpec_32 | B33: Function | C33: The Stock Exchange Application shall connect the Core Application and the Stock Exchange | D33: New | G33: =IF(OR(H33="No",H33=""),"",CONCATENATE(Configuration!$A$2,"_TC_",ROW(B33)-1))
A34: =IF(B34="","",CONCATENATE(Configuration!$A$2,"_",ROW(B34)-1)) -> ATP_ProdSpec_33 | B34: Function | C34: The Stock Exchange Application shall provide a user account for trading | G34: =IF(OR(H34="No",H34=""),"",CONCATENATE(Configuration!$A$2,"_TC_",ROW(B34)-1))
A35: =IF(B35="","",CONCATENATE(Configuration!$A$2,"_",ROW(B35)-1)) -> ATP_ProdSpec_34 | B35: Function | C35: The Stock Exchange Application shall provide stock exchange information | G35: =IF(OR(H35="No",H35=""),"",CONCATENATE(Configuration!$A$2,"_TC_",ROW(B35)-1))
A36: =IF(B36="","",CONCATENATE(Configuration!$A$2,"_",ROW(B36)-1)) -> ATP_ProdSpec_35 | B36: Function | C36: The Stock Exchange Application shall provide stock market news and indicators | G36: =IF(OR(H36="No",H36=""),"",CONCATENATE(Configuration!$A$2,"_TC_",ROW(B36)-1))
A37: =IF(B37="","",CONCATENATE(Configuration!$A$2,"_",ROW(B37)-1)) -> ATP_ProdSpec_36 | B37: Sub-heading | C37: Market Information Application (third-party provider) | G37: =IF(OR(H37="No",H37=""),"",CONCATENATE(Configuration!$A$2,"_TC_",ROW(B37)-1))
A38: =IF(B38="","",CONCATENATE(Configuration!$A$2,"_",ROW(B38)-1)) -> ATP_ProdSpec_37 | B38: Function | C38: The Market Information Application shall connect the Core Application with real-time Market Information | G38: =IF(OR(H38="No",H38=""),"",CONCATENATE(Configuration!$A$2,"_TC_",ROW(B38)-1))
A39: =IF(B39="","",CONCATENATE(Configuration!$A$2,"_",ROW(B39)-1)) -> ATP_ProdSpec_38 | B39: Function | C39: The Market Information Application shall connect the Core Application with current real-time information that could potentially have an impact on the exchange | D39: New | G39: =IF(OR(H39="No",H39=""),"",CONCATENATE(Configuration!$A$2,"_TC_",ROW(B39)-1))
A40: =IF(B40="","",CONCATENATE(Configuration!$A$2,"_",ROW(B40)-1)) -> ATP_ProdSpec_39 | B40: Function | C40: The Market Information Application shall provide the Core Application with training material from experts that can be used to build and further develop a trading knowledge database | G40: =IF(OR(H40="No",H40=""),"",CONCATENATE(Configuration!$A$2,"_TC_",ROW(B40)-1))
A41: =IF(B41="","",CONCATENATE(Configuration!$A$2,"_",ROW(B41)-1)) -> ATP_ProdSpec_40 | B41: Heading | C41: Product and customer functions | D41: Reviewed | G41: =IF(OR(H41="No",H41=""),"",CONCATENATE(Configuration!$A$2,"_TC_",ROW(B41)-1)) | H41: No
A42: =IF(B42="","",CONCATENATE(Configuration!$A$2,"_",ROW(B42)-1)) -> ATP_ProdSpec_41 | B42: Sub-heading | C42: Product Authentication | G42: =IF(OR(H42="No",H42=""),"",CONCATENATE(Configuration!$A$2,"_TC_",ROW(B42)-1))
A43: =IF(B43="","",CONCATENATE(Configuration!$A$2,"_",ROW(B43)-1)) -> ATP_ProdSpec_42 | B43: Information | C43: The product authentication customer function deals with the use cases of secure login to the product and the third-party tools. | G43: =IF(OR(H43="No",H43=""),"",CONCATENATE(Configuration!$A$2,"_TC_",ROW(B43)-1))
A44: =IF(B44="","",CONCATENATE(Configuration!$A$2,"_",ROW(B44)-1)) -> ATP_ProdSpec_43 | B44: Function | C44: When the customer starts the product on their device, a user name and password must be requested for login. | G44: =IF(OR(H44="No",H44=""),"",CONCATENATE(Configuration!$A$2,"_TC_",ROW(B44)-1))
A45: =IF(B45="","",CONCATENATE(Configuration!$A$2,"_",ROW(B45)-1)) -> ATP_ProdSpec_44 | B45: Function | C45: The customer must log in to the product again when the device ends its power lifecycle or the product is closed by an exit command. | G45: =IF(OR(H45="No",H45=""),"",CONCATENATE(Configuration!$A$2,"_TC_",ROW(B45)-1))
A46: =IF(B46="","",CONCATENATE(Configuration!$A$2,"_",ROW(B46)-1)) -> ATP_ProdSpec_45 | B46: Sub-heading | C46: Product Configuation | G46: =IF(OR(H46="No",H46=""),"",CONCATENATE(Configuration!$A$2,"_TC_",ROW(B46)-1))
A47: =IF(B47="","",CONCATENATE(Configuration!$A$2,"_",ROW(B47)-1)) -> ATP_ProdSpec_46 | B47: Information | C47: The product configuration customer function deals with the use cases of configuring the product itself, the third-party tools used and the interface of the third-party tool. | G47: =IF(OR(H47="No",H47=""),"",CONCATENATE(Configuration!$A$2,"_TC_",ROW(B47)-1))
A48: =IF(B48="","",CONCATENATE(Configuration!$A$2,"_",ROW(B48)-1)) -> ATP_ProdSpec_47 | B48: Sub-heading | C48: Product Status | G48: =IF(OR(H48="No",H48=""),"",CONCATENATE(Configuration!$A$2,"_TC_",ROW(B48)-1))
A49: =IF(B49="","",CONCATENATE(Configuration!$A$2,"_",ROW(B49)-1)) -> ATP_ProdSpec_48 | B49: Information | C49: The product status customer function deals with the use cases to determine the status of the product and the third-party tools and to make it visually available to the consumer. | G49: =IF(OR(H49="No",H49=""),"",CONCATENATE(Configuration!$A$2,"_TC_",ROW(B49)-1))
A50: =IF(B50="","",CONCATENATE(Configuration!$A$2,"_",ROW(B50)-1)) -> ATP_ProdSpec_49 | B50: Sub-heading | C50: AI Trading | G50: =IF(OR(H50="No",H50=""),"",CONCATENATE(Configuration!$A$2,"_TC_",ROW(B50)-1))
A51: =IF(B51="","",CONCATENATE(Configuration!$A$2,"_",ROW(B51)-1)) -> ATP_ProdSpec_50 | B51: Information | C51: The customer function AI Trading deals with the use cases of automated and autonomous trading, as well as manual override. | G51: =IF(OR(H51="No",H51=""),"",CONCATENATE(Configuration!$A$2,"_TC_",ROW(B51)-1))
A52: =IF(B52="","",CONCATENATE(Configuration!$A$2,"_",ROW(B52)-1)) -> ATP_ProdSpec_51 | B52: Function | C52: The customer function AI Trading must be made available by the product if the product is in the READY state. | G52: =IF(OR(H52="No",H52=""),"",CONCATENATE(Configuration!$A$2,"_TC_",ROW(B52)-1))
A53: =IF(B53="","",CONCATENATE(Configuration!$A$2,"_",ROW(B53)-1)) -> ATP_ProdSpec_52 | B53: Function | C53: The customer function AI Trading must allow the customer to create multiple instances of AI Traders, which trade different trading classes or different products in the same trading class. | G53: =IF(OR(H53="No",H53=""),"",CONCATENATE(Configuration!$A$2,"_TC_",ROW(B53)-1))
... A59: =IF(B59="","",CONCATENATE(Configuration!$A$2,"_",ROW(B59)-1)) -> ATP_ProdSpec_58 | B59: Information | C59: The customer function product history recording deals with the use cases of recording and logging consumer and trading activities. | G59: =IF(OR(H59="No",H59=""),"",CONCATENATE(Configuration!$A$2,"_TC_",ROW(B59)-1))
A60: =IF(B60="","",CONCATENATE(Configuration!$A$2,"_",ROW(B60)-1)) -> ATP_ProdSpec_59 | B60: Heading | C60: Product user interface | D60: Reviewed | G60: =IF(OR(H60="No",H60=""),"",CONCATENATE(Configuration!$A$2,"_TC_",ROW(B60)-1)) | H60: No
A61: =IF(B61="","",CONCATENATE(Configuration!$A$2,"_",ROW(B61)-1)) | C61: Initialisierung | G61: =IF(OR(H61="No",H61=""),"",CONCATENATE(Configuration!$A$2,"_TC_",ROW(B61)-1))
A62: =IF(B62="","",CONCATENATE(Configuration!$A$2,"_",ROW(B62)-1)) | C62: Hauptbildschirm | G62: =IF(OR(H62="No",H62=""),"",CONCATENATE(Configuration!$A$2,"_TC_",ROW(B62)-1))
A63: =IF(B63="","",CONCATENATE(Configuration!$A$2,"_",ROW(B63)-1)) | C63: Konfigurationsbildschirm | G63: =IF(OR(H63="No",H63=""),"",CONCATENATE(Configuration!$A$2,"_TC_",ROW(B63)-1))
A64: =IF(B64="","",CONCATENATE(Configuration!$A$2,"_",ROW(B64)-1)) | C64: Historische Datenbildschirm | G64: =IF(OR(H64="No",H64=""),"",CONCATENATE(Configuration!$A$2,"_TC_",ROW(B64)-1))
A65: =IF(B65="","",CONCATENATE(Configuration!$A$2,"_",ROW(B65)-1)) -> ATP_ProdSpec_64 | B65: Heading | C65: Applicable documents | D65: Reviewed | G65: =IF(OR(H65="No",H65=""),"",CONCATENATE(Configuration!$A$2,"_TC_",ROW(B65)-1)) | H65: No
A66: =IF(B66="","",CONCATENATE(Configuration!$A$2,"_",ROW(B66)-1)) -> ATP_ProdSpec_65 | B66: Heading | C66: Appendices and references | D66: Reviewed | G66: =IF(OR(H66="No",H66=""),"",CONCATENATE(Configuration!$A$2,"_TC_",ROW(B66)-1)) | H66: No
A67: =IF(B67="","",CONCATENATE(Configuration!$A$2,"_",ROW(B67)-1)) -> ATP_ProdSpec_66 | B67: Information | C67: The product is an application that provides virtual traders. The virtual traders can use trading applications such as Binance, Bitget to carry out automated and autonomous trading of shares, derivatives, crypto, etc. over a period of 24/7 without human intervention. For this purpose, the virtual traders use basic principles, expert and their own practical experience in the field of “technical analysis”. | D67: Reviewed | G67: =IF(OR(H67="No",H67=""),"",CONCATENATE(Configuration!$A$2,"_TC_",ROW(B67)-1))
A68: =IF(B68="","",CONCATENATE(Configuration!$A$2,"_",ROW(B68)-1)) -> ATP_ProdSpec_67 | B68: Function | C68: The product shall be availabe 24/7 | D68: New | G68: =IF(OR(H68="No",H68=""),"",CONCATENATE(Configuration!$A$2,"_TC_",ROW(B68)-1))
A69: =IF(B69="","",CONCATENATE(Configuration!$A$2,"_",ROW(B69)-1)) -> ATP_ProdSpec_68 | B69: Function | C69: The product shall be able to offer trades with real and virtual money | D69: Reviewed | G69: =IF(OR(H69="No",H69=""),"",CONCATENATE(Configuration!$A$2,"_TC_",ROW(B69)-1))
A70: =IF(B70="","",CONCATENATE(Configuration!$A$2,"_",ROW(B70)-1)) | C70: import java.net.NetworkInterface import java.net.InetAddress fun isWirelessConnectionAvailable(): Boolean { return NetworkInterface.getNetworkInterfaces().toList().any { networkInterface -> networkInterface.name.contains("wi", ignoreCase = true) && networkInterface.isUp } } fun hasInternetConnection(): Boolean { return try { val address = InetAddress.getByName("www.google.com") !address.equals("") } catch (e: Exception) { false } } fun main() { if (isWirelessConnectionAvailable()) { println("Wireless connection is available.") if (hasInternetConnection()) { println("Internet connection is available via wireless.") } else { println("No Internet connection is available via wireless.") } } else { println("Wireless connection is not available.") } } Erklärung: NetworkInterface.getNetworkInterfaces(): Diese Methode gibt eine Liste aller Netzwerkinterfaces auf dem System zurück. Du kannst durch diese Liste iterieren und prüfen, ob ein Interface eine Wireless-Verbindung ist und ob es aktiv (isUp). InetAddress.getByName("www.google.com"): Diese Methode versucht, die IP-Adresse der angegebenen Webseite abzurufen. Wenn dies gelingt, wird eine funktionierende Internetverbindung angenommen.
A71: =IF(B71="","",CONCATENATE(Configuration!$A$2,"_",ROW(B71)-1))
A72: =IF(B72="","",CONCATENATE(Configuration!$A$2,"_",ROW(B72)-1))
A73: =IF(B73="","",CONCATENATE(Configuration!$A$2,"_",ROW(B73)-1))
A74: =IF(B74="","",CONCATENATE(Configuration!$A$2,"_",ROW(B74)-1))
A75: =IF(B75="","",CONCATENATE(Configuration!$A$2,"_",ROW(B75)-1))
A76: =IF(B76="","",CONCATENATE(Configuration!$A$2,"_",ROW(B76)-1))
A77: =IF(B77="","",CONCATENATE(Configuration!$A$2,"_",ROW(B77)-1))
A78: =IF(B78="","",CONCATENATE(Configuration!$A$2,"_",ROW(B78)-1))
A79: =IF(B79="","",CONCATENATE(Configuration!$A$2,"_",ROW(B79)-1))
A80: =IF(B80="","",CONCATENATE(Configuration!$A$2,"_",ROW(B80)-1))
A81: =IF(B81="","",CONCATENATE(Configuration!$A$2,"_",ROW(B81)-1))
A82: =IF(B82="","",CONCATENATE(Configuration!$A$2,"_",ROW(B82)-1))
... A543: =IF(B543="","",CONCATENATE(Configuration!$A$2,"_",ROW(B543)-1))

Sheet Configuration
A1: ID Prefix | B1: Requirement Type | C1: Requirement Status | D1: Test Type | E1: Test Status | F1: Product Releases
A2: ATP_ProdSpec | B2: Heading | C2: New | D2: Automatic | E2: New | F2: Release 1.0.0
B3: Information | C3: Changed | D3: Manual | E3: Changed | F3: Release 1.1.0
B4: Function | C4: Review | D4: No | E4: Review
B5: Non Function | C5: Reviewed | E5: Reviewed
B6: Standard | C6: Rejected | E6: Rejected
B7: Sub-heading
B8: Interface
B9: Parameter

Sheet KPI
